{
  "data": [
    {
      "timestamp": 1609459200000,
      "Primary Education Multi Level (Public)": 19891,
      "Primary Education Multi Level (Private)": 181,
      "Primary Education Single Level (Public)": 120339,
      "Primary Education Single Level (Private)": 12275
    }
  ],
  "code": "LESMIS_num_primary_classrooms",
  "legacy": false,
  "reportCode": "LESMIS_num_primary_classrooms",
  "name": "Number of Primary School Classrooms",
  "type": "chart",
  "xName": "Year",
  "yName": "Number of Classrooms",
  "chartType": "line",
  "valueType": "number",
  "chartConfig": {
    "Primary Education Multi Level (Public)": { "color": "#ff9800", "legendOrder": 3 },
    "Primary Education Multi Level (Private)": { "color": "#ffc107", "legendOrder": 4 },
    "Primary Education Single Level (Public)": { "color": "#e91e63", "legendOrder": 1 },
    "Primary Education Single Level (Private)": { "color": "#ff5722", "legendOrder": 2 }
  },
  "periodGranularity": "year"
}
